{
  "100": "<fieldpine-create-widget description=\"This is the current store\" id=\"100\" name=\"MembershipOpto1\" type=\"link\">\n<div class=\"opto\">\n<a href=\"/report/rr/cartworldaus/sshome.htm\">\nFranchise Report\n</a>\n</div>\n</fieldpine-create-widget>",
  "101": "<fieldpine-create-widget id=\"101\" name=\"Advisor Link\" type=\"link\">\n<div class=\"opto\" style=\"overflow:hidden\">\n<a href=\"sshome_advisor.htm\">\nAdvisor\n</a>\n</div>\n</fieldpine-create-widget>",
    "102": "<fieldpine-create-widget id=\"102\" name=\"Email Interfaces Link\" type=\"link\">\n<div class=\"opto\" style=\"overflow:hidden\">\n<a href=\"sshome_email.htm\">\nEmail & Interfaces\n</a>\n</div>\n</fieldpine-create-widget>",
  "10000": "<fieldpine-create-widget description=\"Allow user to select which store this browser is operating in if it cannot be determined automatically\" id=\"10000\" name=\"Select Store\" type=\"link\">\n<div class=\"opto\" id=\"widget-select-store\">\n<a href=\"#\" onclick=\"SelectStore(); return false;\">\n<span>Select Store</span>\n</a>\n</div>\n</fieldpine-create-widget>",
  "10001": "<fieldpine-create-widget description=\"Main products maintainence page\" id=\"10001\" name=\"Products Menu Page\" type=\"link\">\n<div class=\"opto\">\n<a href=\"sshome_products.htm\">\n<span>Products</span>\n</a>\n</div>\n</fieldpine-create-widget>",
  "10032": "<fieldpine-create-widget description=\"Loyalty menu page\" id=\"10032\" name=\"Loyalty\" type=\"link\">\n<div class=\"opto\" data-fdl-sec=\"ne,d\" id=\"widget-loyalty\">\n<a href=\"sshome_loyalty.htm\">Loyalty</a>\n</div>\n</fieldpine-create-widget>",
  "10030": "<fieldpine-create-widget description=\"Customers menu page\" id=\"10030\" name=\"Customers\" type=\"link\">\n<div class=\"opto\" id=\"widget-customers\">\n<a href=\"sshome_customers.htm\">Customers</a>\n</div>\n</fieldpine-create-widget>",
  "10031": "<fieldpine-create-widget description=\"Suppliers menu page\" id=\"10031\" name=\"Suppliers\" type=\"link\">\n<div class=\"opto\" id=\"widget-suppliers\">\n<a href=\"sshome_suppliers.htm\"><p>Suppliers</p></a>\n</div>\n</fieldpine-create-widget>",
  "10003": "<fieldpine-create-widget id=\"10003\" name=\"Marketing Programs\" style=\"display: none;\" type=\"link\">\n<div class=\"opto\" data-fdl-sec=\"ne,d\">\n<a href=\"sshome_marketingprograms.htm\">Marketing Programs</a>\n</div>\n</fieldpine-create-widget>",
  "10004": "<fieldpine-create-widget description=\"Menu for management of prepay/gift cards\" id=\"10004\" name=\"Prepay Card\" type=\"link\">\n<div class=\"opto\" data-fdl-sec=\"ne,d\">\n<a href=\"sshome_prepay.htm\"><p>Prepay</p></a>\n</div>\n</fieldpine-create-widget>",
  "10005": "<fieldpine-create-widget description=\"Functionality broadly related to active selling\" id=\"10005\" name=\"Selling\" type=\"link\">\n<div class=\"opto\">\n<a href=\"sshome_sell.htm\">Selling</a>\n</div>\n</fieldpine-create-widget>",
  "10006": "<fieldpine-create-widget description=\"Options for Franchise members\" id=\"10006\" name=\"Franchisee\" type=\"link\">\n<div class=\"opto\">\n<a href=\"sshome_franchisee.htm\">Franchisee</a>\n</div>\n</fieldpine-create-widget>",
  "10007": "<fieldpine-create-widget description=\"Options to configure system operation\" id=\"10007\" name=\"Settings\" type=\"link\">\n<div class=\"opto\">\n<a href=\"sshome_settings.htm\">Settings</a>\n</div>\n</fieldpine-create-widget>",
  "10010": "<fieldpine-create-widget description=\"\" id=\"10010\" name=\"Interfaces\" type=\"link\">\n<div class=\"opto dis\" id=\"interface\">\n<a href=\"#\" onclick=\"CountFreq(this)\">Interfaces</a>\n</div>\n</fieldpine-create-widget>",
  "10011": "<fieldpine-create-widget description=\"\" id=\"10011\" name=\"Operations Monitoring\" type=\"link\">\n<div class=\"opto\" id=\"opsmon\">\n<a href=\"sshome_opsmon.htm\">Operations Monitoring</a>\n</div>\n</fieldpine-create-widget>",
  "10012": "<fieldpine-create-widget description=\"Advanced options for developers around interface APIs\" id=\"10012\" name=\"API\" type=\"link\">\n<div class=\"opto\" id=\"API\">\n<a href=\"sshome_api.htm\" onclick=\"CountFreq(this)\">API</a>\n</div>\n</fieldpine-create-widget>",
  "10013": "<fieldpine-create-widget description=\"\" id=\"10013\" name=\"Transaction Log\" type=\"link\">\n<div class=\"opto\" id=\"tranlog\">\n<a href=\"sshome_transactions.htm\" onclick=\"CountFreq(this)\">Transaction Log</a>\n</div>\n</fieldpine-create-widget>",
  "10014": "<fieldpine-create-widget description=\"\" id=\"10014\" name=\"Request Journal\" type=\"link\">\n<div class=\"opto\" id=\"jourlog\">\n<a href=\"sshome_transaction_journal.htm\" onclick=\"CountFreq(this)\">Request Journal</a>\n</div>\n</fieldpine-create-widget>",
  "10015": "<fieldpine-create-widget description=\"\" id=\"10015\" name=\"System Commanding\" type=\"link\">\n<div class=\"opto\">\n<a href=\"sshome_systemcommanding.htm\">System Commanding</a>\n</div>\n</fieldpine-create-widget>",
  "10016": "<fieldpine-create-widget description=\"\" id=\"10016\" name=\"Addins\" type=\"link\">\n<div class=\"opto\">\n<a href=\"sshome_addins.htm\">Addins</a>\n</div>\n</fieldpine-create-widget>",
  "10020": "<fieldpine-create-widget description=\"\" id=\"10020\" name=\"Signs\" type=\"link\">\n<div class=\"opto\">\n<a href=\"sshome_signs.htm\">Signs and Labels</a>\n</div>\n</fieldpine-create-widget>",
  "10021": "<fieldpine-create-widget description=\"\" id=\"10021\" name=\"Fieldpine Account\" type=\"link\">\n<div class=\"opto\">\n<a href=\"/report/rr/sshome_fieldpineaccount.htm\">Fieldpine Account</a>\n</div>\n</fieldpine-create-widget>",
  "10022": "<fieldpine-create-widget description=\"\" id=\"10022\" name=\"Vehicles\" type=\"link\">\n<div class=\"opto\">\n<a href=\"sshome_vehicles.htm\">Vehicles</a>\n</div>\n</fieldpine-create-widget>",
  "10023": "<fieldpine-create-widget description=\"\" id=\"10023\" name=\"Service and Repairs\" type=\"link\">\n<div class=\"opto dis\">\n<a href=\"sshome_service.htm\">Service and Repairs</a>\n</div>\n</fieldpine-create-widget>",
  "10024": "<fieldpine-create-widget description=\"\" id=\"10024\" name=\"Industry Benchmarks\" type=\"link\">\n<div class=\"opto dis\">\n<a href=\"sshome_m4benchmark.htm\">Industry Benchmarks</a>\n</div>\n</fieldpine-create-widget>",
  "10027": "<fieldpine-create-widget description=\"\" id=\"10027\" name=\"Live Results\" style=\"display: none;\" type=\"link\">\n<div class=\"opto\">\n<a href=\"/report/pos/external/fieldpine/ss_liveresults.htm\">Live Results</a>\n</div>\n</fieldpine-create-widget>",
  "10028": "<fieldpine-create-widget description=\"\" id=\"10028\" name=\"Online Receipts\" style=\"display: none;\" type=\"link\">\n<div class=\"opto dis\">\n<a href=\"/report/pos/external/fieldpine/ss_onlinereceipts.htm\">Online Receipts</a>\n</div>\n</fieldpine-create-widget>",
  "10029": "<fieldpine-create-widget description=\"\" id=\"10029\" name=\"Memberships\" type=\"link\">\n<div class=\"opto\">\n<a href=\"/report/pos/external/fieldpine/ss_memberships.htm\">Memberships</a>\n</div>\n</fieldpine-create-widget>",
  "topbar": "<fieldpine-create-widget description=\"Topbar UI\" id=\"topbar\" name=\"TopbarWidget\" type=\"html\">\n<div class=\"topbar\">\n  <div class=\"left-section\">\n    <img id=\"topbarlogo\" src=\"https://www.cartridgeworld.co.nz/images/cw-logo-1x.png\" alt=\"Cartridge World Logo\" style=\"height:48px;width:auto;border-radius:8px;box-shadow:4px 4px 8px #\" />\n    <small>(Release# <span id=\"gds_server_version\">340</span>)</small>\n  </div>\n  <div class=\"right-section\">\n    <span id=\"loginbut\" style=\"display:none\"><input type=\"button\" value=\"Login\" onclick=\"OptLogin()\" /></span>\n    <span id=\"sstype\"></span>\n    <span id=\"gdsstatus\"></span>\n  </div>\n</div>\n</fieldpine-create-widget>",
  "sale_entry": "<fieldpine-create-widget description=\"Enter a Sale\" id=\"sale_entry\" name=\"SaleEntryWidget\" type=\"link\">\n<a class=\"bigbut\" href=\"/report/rr/sell5.htm\">\n  <h2>Enter a Sale</h2>\n  <span class=\"material-icons\">point_of_sale</span>\n  <p>Capture a sale</p>\n</a>\n</fieldpine-create-widget>",
  "sales_report": "<fieldpine-create-widget description=\"Sales Report\" id=\"sales_report\" name=\"SalesReportWidget\" type=\"link\">\n<a class=\"bigbut\" href=\"salesflat_review.htm\">\n  <h2>Sales Report</h2>\n  <span class=\"material-icons\">bar_chart</span>\n  <p>View Completed Sales</p>\n</a>\n</fieldpine-create-widget>",
  "commission_report": "<fieldpine-create-widget description=\"Commission Report\" id=\"commission_report\" name=\"CommissionReportWidget\" type=\"link\">\n<a class=\"bigbut\" href=\"franchiseagency.htm\">\n  <h2>Commission Report</h2>\n  <span class=\"material-icons\">receipt_long</span>\n  <p>Monthly Report</p>\n</a>\n</fieldpine-create-widget>",
  "stock_levels": "<fieldpine-create-widget description=\"Stock Levels\" id=\"stock_levels\" name=\"StockLevelsWidget\" type=\"link\">\n<a class=\"bigbut\" href=\"stocklevels.htm\">\n  <h2>Stock Levels</h2>\n  <span class=\"material-icons\">inventory</span>\n  <p>Store Stock Levels</p>\n</a>\n</fieldpine-create-widget>",
  "topbar_back_button": "<fieldpine-create-widget description=\"Back Button\" id=\"topbar_back_button\" name=\"TopbarBackButton\" type=\"html\">\n<button onclick=\"history.back()\" style=\"background-color: RGB(255,233,15); color: black; border: none; padding: 8px 16px; border-radius: 4px; cursor: pointer; font-size: 1em; margin-left: 1em;\">\n\u2190 Back\n</button>\n</fieldpine-create-widget>"
}